fa_purity/__init__.py
fa_purity/_bug.py
fa_purity/date_time.py
fa_purity/lock.py
fa_purity/py.typed
fa_purity/_core/__init__.py
fa_purity/_core/bool.py
fa_purity/_core/cmd.py
fa_purity/_core/coproduct.py
fa_purity/_core/frozen.py
fa_purity/_core/iter_factory.py
fa_purity/_core/maybe.py
fa_purity/_core/result.py
fa_purity/_core/unit.py
fa_purity/_core/unsafe.py
fa_purity/_core/utils.py
fa_purity/_core/pure_iter/__init__.py
fa_purity/_core/pure_iter/_core.py
fa_purity/_core/pure_iter/_factory.py
fa_purity/_core/stream/__init__.py
fa_purity/_core/stream/_core.py
fa_purity/_core/stream/_factory.py
fa_purity/_transform/__init__.py
fa_purity/_transform/cmd.py
fa_purity/_transform/cmd_smash.py
fa_purity/_transform/coproduct.py
fa_purity/_transform/pure_iter.py
fa_purity/_transform/result.py
fa_purity/_transform/result_smash.py
fa_purity/_transform/stream.py
fa_purity/json/__init__.py
fa_purity/json/_core/__init__.py
fa_purity/json/_core/primitive.py
fa_purity/json/_core/value.py
fa_purity/json/_transform/__init__.py
fa_purity/json/_transform/primitive/__init__.py
fa_purity/json/_transform/primitive/_factory.py
fa_purity/json/_transform/primitive/_transform.py
fa_purity/json/_transform/value/__init__.py
fa_purity/json/_transform/value/_transform.py
fa_purity/json/_transform/value/_factory/__init__.py
fa_purity/json/_transform/value/_factory/_common.py
fa_purity/json/_transform/value/_factory/_jval_factory.py
fa_purity/json/_transform/value/_factory/_unfolded_factory.py
fa_purity-2.5.2.dist-info/WHEEL
fa_purity-2.5.2.dist-info/METADATA
fa_purity-2.5.2.dist-info/RECORD
