Metadata-Version: 2.4
Name: fa_purity
Version: 2.5.2
Summary: Pure functional and typing utilities
Author-email: Product Team <development@fluidattacks.com>
Requires-Python: >=3.11
Classifier: License :: OSI Approved :: MIT License
Requires-Dist: Deprecated >=1.2.12, <2.0.0
Requires-Dist: more-itertools >=8.10.0, <11.0.0
Requires-Dist: simplejson >=3.17.6, <4.0.0
